MeshFlash/__init__.py
MeshFlash/__main__.py
MeshFlash-1.2.dist-info/LICENSE
MeshFlash-1.2.dist-info/METADATA
MeshFlash-1.2.dist-info/WHEEL
MeshFlash-1.2.dist-info/entry_points.txt
MeshFlash-1.2.dist-info/top_level.txt
MeshFlash-1.2.dist-info/RECORD
