Metadata-Version: 2.1
Name: MeshFlash
Version: 1.2
Summary: Meshtastic Utility for flashing radios
Home-page: https://github.com/ZebusJesus/MeshFlash
Author: Zebus Jeus
Author-email: ZebusJeus@pm.me
License: MIT
Platform: UNKNOWN
Classifier: License :: OSI Approved :: MIT License
Classifier: Programming Language :: Python :: 3
Classifier: Programming Language :: Python :: 3.7
Requires-Python: >=3.6
License-File: LICENSE
Requires-Dist: PySimpleGUI (>=4.34.0)
Requires-Dist: requests (>=2.25.1)
Requires-Dist: esptool (>=3.0)
Requires-Dist: pypubsub
